README.txt
setup.cfg
setup.py
docs/HISTORY.txt
indra/__init__.py
indra.base.egg-info/PKG-INFO
indra.base.egg-info/SOURCES.txt
indra.base.egg-info/dependency_links.txt
indra.base.egg-info/entry_points.txt
indra.base.egg-info/namespace_packages.txt
indra.base.egg-info/requires.txt
indra.base.egg-info/top_level.txt
indra.base.egg-info/zip-safe
indra/base/__init__.py
indra/base/cllsd_test.py
indra/base/config.py
indra/base/lllog.py
indra/base/llsd.py
indra/base/lluuid.py
indra/base/metrics.py
indra/base/tests/__init__.py
indra/base/tests/indrabase.txt
indra/base/tests/testDocTests.py