Metadata-Version: 1.0
Name: indra.base
Version: 1.0
Summary: Second Life/OGP support library for handling uuid and llsd
Home-page: http://wiki.secondlife.com/wiki
Author: Linden Lab
Author-email: info@lindenlab.com
License: MIT License
Keywords: lindenlab secondlife ogp llsd lluuid uuid indra
Platform: UNKNOWN
Classifier: Programming Language :: Python
Classifier: Topic :: Software Development :: Libraries :: Python Modules
